testclient/__init__.py
testclient/main.py
testclient/utils.py
ogcldapi_testclient-0.5.dist-info/METADATA
ogcldapi_testclient-0.5.dist-info/WHEEL
ogcldapi_testclient-0.5.dist-info/top_level.txt
ogcldapi_testclient-0.5.dist-info/RECORD
