Metadata-Version: 2.1
Name: ogcldapi-testclient
Version: 0.5
Summary: A test client (command line program) for implementations of the "OGC LD API" which is a variant of the standardised OGC API: Features that delivers OGC API data and also Linked Data..
Home-page: https://github.com/surroundaustralia/ogcldapi-testclient
Author: Nicholas Car
Author-email: nicholas.car@surroundaustralia.com
License: LICENSE
Download-URL: https://github.com/surroundaustralia/ogcldapi-testclient/archive/0.5.tar.gz
Project-URL: Bug Reports, https://github.com/surroundaustralia/ogcldapi-testclient/issues
Project-URL: Source, https://github.com/surroundaustralia/ogcldapi-testclient/
Keywords: Open Geospatial Consortium,Open API,OGC API,Semantic Web,Linked Data API
Platform: UNKNOWN
Classifier: Development Status :: 4 - Beta
Classifier: Topic :: Utilities
Classifier: License :: OSI Approved :: GNU General Public License v3 or later (GPLv3+)
Classifier: Intended Audience :: Developers
Classifier: Natural Language :: English
Classifier: Programming Language :: Python :: 3
Classifier: Programming Language :: Python :: 3 :: Only
Classifier: Programming Language :: Python :: 3.6
Classifier: Programming Language :: Python :: 3.7
Classifier: Programming Language :: Python :: Implementation :: CPython
Classifier: Programming Language :: Python :: Implementation :: PyPy
Classifier: Topic :: Software Development :: Libraries :: Python Modules
